xkivy/__init__.py
xkivy/colors.py
xkivy/version.py
xkivy/effects/__init__.py
xkivy/effects/clickeffect.py
xkivy/effects/scrolleffect.py
xkivy/effects/shadoweffect.py
xkivy/effects/uixeffect.py
xkivy/properties/__init__.py
xkivy/thread_utils/__init__.py
xkivy/uix/__init__.py
xkivy/uix/button.py
xkivy/uix/dialog.py
xkivy/uix/dropdown.py
xkivy/uix/icon.py
xkivy/uix/image.py
xkivy/uix/label.py
xkivy/uix/layouts.py
xkivy/uix/navigation.py
xkivy/uix/popup.py
xkivy/uix/screenmanager.py
xkivy/uix/scrollview.py
xkivy/uix/sweeper.py
xkivy/uix/textfield.py
xkivy/utils/__init__.py
xkivy/utils/controller.py
xkivy/utils/touchmanager.py
xkivy-1.1.1.dist-info/LICENSE
xkivy-1.1.1.dist-info/METADATA
xkivy-1.1.1.dist-info/WHEEL
xkivy-1.1.1.dist-info/top_level.txt
xkivy-1.1.1.dist-info/RECORD
