Metadata-Version: 2.1
Name: xkivy
Version: 1.1.1
Summary: A kivy extension module to add functionality and making new widgets accessible to both kivy and kivymd.
Author-email: Brian Musakwa <digreatbrian@gmail.com>
Project-URL: Homepage, https://github.com/digreatbrian/xkivy
Project-URL: Bug Tracker, https://github.com/digreatbrian/xkivy/issues
Project-URL: UIX Docs, https://github.com/digreatbrian/xkivy/blob/main/UIXDocumentation.md
Keywords: kivy,xkivy,app,kivymd
Classifier: Programming Language :: Python :: 3
Classifier: License :: OSI Approved :: MIT License
Classifier: Operating System :: OS Independent
Requires-Python: >=3.7
License-File: LICENSE
